hero_card/__init__.py
hero_card/frontend/build/asset-manifest.json
hero_card/frontend/build/bootstrap.min.css
hero_card/frontend/build/index.html
hero_card/frontend/build/static/css/main.2e90ffcc.css
hero_card/frontend/build/static/css/main.2e90ffcc.css.map
hero_card/frontend/build/static/js/main.40883e19.js
hero_card/frontend/build/static/js/main.40883e19.js.LICENSE.txt
hero_card/frontend/build/static/js/main.40883e19.js.map
card_component_hero-0.0.14.dist-info/LICENSE
card_component_hero-0.0.14.dist-info/METADATA
card_component_hero-0.0.14.dist-info/WHEEL
card_component_hero-0.0.14.dist-info/top_level.txt
card_component_hero-0.0.14.dist-info/RECORD
