Metadata-Version: 2.1
Name: card-component-hero
Version: 0.0.14
Home-page: 
Author: 
Author-email: 
Requires-Python: >=3.7
License-File: LICENSE
Requires-Dist: streamlit (>=0.63)
